{
  "project_info": {
    "project_number": "1028744098176",
    "firebase_url": "https://sign-in-3096e.firebaseio.com",
    "project_id": "sign-in-3096e",
    "storage_bucket": "sign-in-3096e.appspot.com"
  },
  "client": [
    {
      "client_info": {
        "mobilesdk_app_id": "1:1028744098176:android:6d4399d23d8e36d0721165",
        "android_client_info": {
          "package_name": "com.example.sign_in"
        }
      },
      "oauth_client": [
        {
          "client_id": "1028744098176-49svsvkg98g8vm28eq3n4u7hr02hhja7.apps.googleusercontent.com",
          "client_type": 1,
          "android_info": {
            "package_name": "com.example.sign_in",
            "certificate_hash": "05c988822365dfac390481177848a2b8da3ecf1d"
          }
        },
        {
          "client_id": "1028744098176-1s1h6ea98uqedlrkifraurclh4f90n95.apps.googleusercontent.com",
          "client_type": 3
        }
      ],
      "api_key": [
        {
          "current_key": "AIzaSyDGAz0qRIq5NxzWH-jZMPyPIhsKFSYnTX8"
        }
      ],
      "services": {
        "appinvite_service": {
          "other_platform_oauth_client": [
            {
              "client_id": "1028744098176-1s1h6ea98uqedlrkifraurclh4f90n95.apps.googleusercontent.com",
              "client_type": 3
            }
          ]
        }
      }
    }
  ],
  "configuration_version": "1"
}